[{
  "_id": {
    "$oid": "666c474b2b443a6545da90b4"
  },
  "review_id": {
    "$oid": "666c474b2b443a6545da90b0"
  },
  "question_id": {
    "$oid": "666c33e52b443a6545da9099"
  },
  "answer": "fdfdsfds"
},
{
  "_id": {
    "$oid": "666c474b2b443a6545da90b3"
  },
  "review_id": {
    "$oid": "666c474b2b443a6545da90b0"
  },
  "question_id": {
    "$oid": "666c33de2b443a6545da9098"
  },
  "answer": "abc"
},
{
  "_id": {
    "$oid": "666c484c2b443a6545da90b9"
  },
  "review_id": {
    "$oid": "666c484c2b443a6545da90b5"
  },
  "question_id": {
    "$oid": "666c33e52b443a6545da9099"
  },
  "answer": "fdfdsfds"
},
{
  "_id": {
    "$oid": "666c484c2b443a6545da90b8"
  },
  "review_id": {
    "$oid": "666c484c2b443a6545da90b5"
  },
  "question_id": {
    "$oid": "666c33de2b443a6545da9098"
  },
  "answer": "abc"
},
{
  "_id": {
    "$oid": "666c48832b443a6545da90be"
  },
  "review_id": {
    "$oid": "666c48832b443a6545da90ba"
  },
  "question_id": {
    "$oid": "666c33e52b443a6545da9099"
  },
  "answer": "fdfdsfds"
},
{
  "_id": {
    "$oid": "666c48832b443a6545da90bd"
  },
  "review_id": {
    "$oid": "666c48832b443a6545da90ba"
  },
  "question_id": {
    "$oid": "666c33de2b443a6545da9098"
  },
  "answer": "abc"
},
{
  "_id": {
    "$oid": "666c568c2b443a6545da90c3"
  },
  "review_id": {
    "$oid": "666c568c2b443a6545da90bf"
  },
  "question_id": {
    "$oid": "666c33e52b443a6545da9099"
  },
  "answer": "fdfdsfds"
},
{
  "_id": {
    "$oid": "666c568c2b443a6545da90c2"
  },
  "review_id": {
    "$oid": "666c568c2b443a6545da90bf"
  },
  "question_id": {
    "$oid": "666c33de2b443a6545da9098"
  },
  "answer": "abc"
},
{
  "_id": {
    "$oid": "666c56b82b443a6545da90c8"
  },
  "review_id": {
    "$oid": "666c56b82b443a6545da90c4"
  },
  "question_id": {
    "$oid": "666c33e52b443a6545da9099"
  },
  "answer": "fdfdsfds"
},
{
  "_id": {
    "$oid": "666c56b82b443a6545da90c7"
  },
  "review_id": {
    "$oid": "666c56b82b443a6545da90c4"
  },
  "question_id": {
    "$oid": "666c33de2b443a6545da9098"
  },
  "answer": "abc"
}]